exe.py
updater_exe.py
mcptool/__init__.py
mcptool/__main__.py
mcptool/modules/commands/__init__.py
mcptool/modules/commands/bruteauth.py
mcptool/modules/commands/brutercon.py
mcptool/modules/commands/checker.py
mcptool/modules/commands/clear.py
mcptool/modules/commands/clearservers.py
mcptool/modules/commands/connect.py
mcptool/modules/commands/discord.py
mcptool/modules/commands/dnslookup.py
mcptool/modules/commands/fakeproxy.py
mcptool/modules/commands/help.py
mcptool/modules/commands/iphistory.py
mcptool/modules/commands/ipinfo.py
mcptool/modules/commands/kick.py
mcptool/modules/commands/kickall.py
mcptool/modules/commands/language.py
mcptool/modules/commands/listening.py
mcptool/modules/commands/proxy.py
mcptool/modules/commands/rcon.py
mcptool/modules/commands/resolver.py
mcptool/modules/commands/scan.py
mcptool/modules/commands/seeker.py
mcptool/modules/commands/sendcmd.py
mcptool/modules/commands/server.py
mcptool/modules/commands/settings.py
mcptool/modules/commands/subdomains.py
mcptool/modules/commands/uuid.py
mcptool/modules/commands/websearch.py
mcptool/modules/utilities/__init__.py
mcptool/modules/utilities/banners/__init__.py
mcptool/modules/utilities/banners/banners.py
mcptool/modules/utilities/banners/show_banner.py
mcptool/modules/utilities/commands/__init__.py
mcptool/modules/utilities/commands/validate.py
mcptool/modules/utilities/constants/__init__.py
mcptool/modules/utilities/constants/constants_utilities.py
mcptool/modules/utilities/constants/update_available.py
mcptool/modules/utilities/dns/get_dns_records.py
mcptool/modules/utilities/hackertarget/get_subdomains.py
mcptool/modules/utilities/input/get.py
mcptool/modules/utilities/ip/__init__.py
mcptool/modules/utilities/ip/get_cloudflare_ips.py
mcptool/modules/utilities/ip/get_ip_info.py
mcptool/modules/utilities/managers/__init__.py
mcptool/modules/utilities/managers/language_utils.py
mcptool/modules/utilities/minecraft/__init__.py
mcptool/modules/utilities/minecraft/bot/server_response.py
ncptool-1.0.4.dist-info/LICENSE
ncptool-1.0.4.dist-info/METADATA
ncptool-1.0.4.dist-info/WHEEL
ncptool-1.0.4.dist-info/entry_points.txt
ncptool-1.0.4.dist-info/top_level.txt
ncptool-1.0.4.dist-info/RECORD
